large_image/__init__.py
large_image/config.py
large_image/constants.py
large_image/exceptions.py
large_image/cache_util/__init__.py
large_image/cache_util/base.py
large_image/cache_util/cache.py
large_image/cache_util/cachefactory.py
large_image/cache_util/memcache.py
large_image/cache_util/rediscache.py
large_image/tilesource/__init__.py
large_image/tilesource/base.py
large_image/tilesource/geo.py
large_image/tilesource/jupyter.py
large_image/tilesource/resample.py
large_image/tilesource/stylefuncs.py
large_image/tilesource/tiledict.py
large_image/tilesource/tileiterator.py
large_image/tilesource/utilities.py
large_image/widgets/CompositeLayers.vue
large_image/widgets/DualInput.vue
large_image/widgets/FrameSelector.vue
large_image/widgets/HistogramEditor.vue
large_image/widgets/colors.json
large_image/widgets/components.py
large_image-1.34.0.dist-info/licenses/LICENSE
large_image-1.34.0.dist-info/licenses/NOTICE
large_image-1.34.0.dist-info/METADATA
large_image-1.34.0.dist-info/WHEEL
large_image-1.34.0.dist-info/top_level.txt
large_image-1.34.0.dist-info/RECORD
