Metadata-Version: 2.4
Name: large-image
Version: 1.34.0
Summary: Python modules to work with large, multiresolution images.
Home-page: https://github.com/girder/large_image
Author: Kitware, Inc.
Author-email: kitware@kitware.com
License: Apache-2.0
Keywords: large_image
Classifier: Development Status :: 5 - Production/Stable
Classifier: Programming Language :: Python :: 3
Classifier: Programming Language :: Python :: 3.10
Classifier: Programming Language :: Python :: 3.11
Classifier: Programming Language :: Python :: 3.12
Classifier: Programming Language :: Python :: 3.13
Classifier: Programming Language :: Python :: 3.14
Requires-Python: >=3.10
License-File: LICENSE
License-File: NOTICE
Requires-Dist: cachetools
Requires-Dist: palettable
Requires-Dist: Pillow>=10.3
Requires-Dist: numpy
Requires-Dist: typing-extensions
Provides-Extra: memcached
Requires-Dist: pylibmc>=1.5.1; platform_system != "Windows" and extra == "memcached"
Provides-Extra: redis
Requires-Dist: redis>=4.5.5; extra == "redis"
Provides-Extra: converter
Requires-Dist: large-image-converter>=1.34.0; extra == "converter"
Provides-Extra: colormaps
Requires-Dist: matplotlib; extra == "colormaps"
Requires-Dist: tol-colors>=2.0.0; extra == "colormaps"
Provides-Extra: jupyter
Requires-Dist: aiohttp; extra == "jupyter"
Requires-Dist: ipyvue; extra == "jupyter"
Requires-Dist: ipyleaflet; extra == "jupyter"
Provides-Extra: tiledoutput
Requires-Dist: pyvips; extra == "tiledoutput"
Provides-Extra: performance
Requires-Dist: psutil>=4.2.0; extra == "performance"
Requires-Dist: simplejpeg; extra == "performance"
Provides-Extra: bioformats
Requires-Dist: large-image-source-bioformats>=1.34.0; extra == "bioformats"
Provides-Extra: deepzoom
Requires-Dist: large-image-source-deepzoom>=1.34.0; extra == "deepzoom"
Provides-Extra: dicom
Requires-Dist: large-image-source-dicom>=1.34.0; extra == "dicom"
Provides-Extra: dummy
Requires-Dist: large-image-source-dummy>=1.34.0; extra == "dummy"
Provides-Extra: gdal
Requires-Dist: large-image-source-gdal>=1.34.0; extra == "gdal"
Provides-Extra: mapnik
Requires-Dist: large-image-source-mapnik>=1.34.0; extra == "mapnik"
Provides-Extra: multi
Requires-Dist: large-image-source-multi>=1.34.0; extra == "multi"
Provides-Extra: nd2
Requires-Dist: large-image-source-nd2>=1.34.0; extra == "nd2"
Provides-Extra: ometiff
Requires-Dist: large-image-source-ometiff>=1.34.0; extra == "ometiff"
Provides-Extra: openjpeg
Requires-Dist: large-image-source-openjpeg>=1.34.0; extra == "openjpeg"
Provides-Extra: openslide
Requires-Dist: large-image-source-openslide>=1.34.0; extra == "openslide"
Provides-Extra: pil
Requires-Dist: large-image-source-pil>=1.34.0; extra == "pil"
Provides-Extra: rasterio
Requires-Dist: large-image-source-rasterio>=1.34.0; extra == "rasterio"
Provides-Extra: test
Requires-Dist: large-image-source-test>=1.34.0; extra == "test"
Provides-Extra: tiff
Requires-Dist: large-image-source-tiff>=1.34.0; extra == "tiff"
Provides-Extra: tifffile
Requires-Dist: large-image-source-tifffile>=1.34.0; extra == "tifffile"
Provides-Extra: vips
Requires-Dist: large-image-source-vips>=1.34.0; extra == "vips"
Provides-Extra: zarr
Requires-Dist: large-image-source-zarr>=1.34.0; extra == "zarr"
Provides-Extra: sources
Requires-Dist: large-image-source-bioformats>=1.34.0; extra == "sources"
Requires-Dist: large-image-source-vips>=1.34.0; extra == "sources"
Requires-Dist: large-image-source-nd2>=1.34.0; extra == "sources"
Requires-Dist: large-image-source-dicom>=1.34.0; extra == "sources"
Requires-Dist: large-image-source-openslide>=1.34.0; extra == "sources"
Requires-Dist: large-image-source-openjpeg>=1.34.0; extra == "sources"
Requires-Dist: large-image-source-pil>=1.34.0; extra == "sources"
Requires-Dist: large-image-source-rasterio>=1.34.0; extra == "sources"
Requires-Dist: large-image-source-zarr>=1.34.0; extra == "sources"
Requires-Dist: large-image-source-gdal>=1.34.0; extra == "sources"
Requires-Dist: large-image-source-mapnik>=1.34.0; extra == "sources"
Requires-Dist: large-image-source-test>=1.34.0; extra == "sources"
Requires-Dist: large-image-source-dummy>=1.34.0; extra == "sources"
Requires-Dist: large-image-source-multi>=1.34.0; extra == "sources"
Requires-Dist: large-image-source-tifffile>=1.34.0; extra == "sources"
Requires-Dist: large-image-source-tiff>=1.34.0; extra == "sources"
Requires-Dist: large-image-source-deepzoom>=1.34.0; extra == "sources"
Requires-Dist: large-image-source-ometiff>=1.34.0; extra == "sources"
Provides-Extra: all
Requires-Dist: large-image-source-rasterio[all]>=1.34.0; extra == "all"
Requires-Dist: large-image-source-vips>=1.34.0; extra == "all"
Requires-Dist: ipyvue; extra == "all"
Requires-Dist: large-image-source-dicom>=1.34.0; extra == "all"
Requires-Dist: large-image-source-rasterio>=1.34.0; extra == "all"
Requires-Dist: large-image-source-openjpeg>=1.34.0; extra == "all"
Requires-Dist: pylibmc>=1.5.1; platform_system != "Windows" and extra == "all"
Requires-Dist: large-image-source-test>=1.34.0; extra == "all"
Requires-Dist: large-image-source-multi>=1.34.0; extra == "all"
Requires-Dist: psutil>=4.2.0; extra == "all"
Requires-Dist: aiohttp; extra == "all"
Requires-Dist: large-image-source-pil[all]>=1.34.0; extra == "all"
Requires-Dist: simplejpeg; extra == "all"
Requires-Dist: redis>=4.5.5; extra == "all"
Requires-Dist: large-image-source-tiff[all]>=1.34.0; extra == "all"
Requires-Dist: large-image-source-bioformats>=1.34.0; extra == "all"
Requires-Dist: pyvips; extra == "all"
Requires-Dist: large-image-source-nd2>=1.34.0; extra == "all"
Requires-Dist: matplotlib; extra == "all"
Requires-Dist: large-image-source-openslide>=1.34.0; extra == "all"
Requires-Dist: large-image-source-pil>=1.34.0; extra == "all"
Requires-Dist: ipyleaflet; extra == "all"
Requires-Dist: large-image-source-zarr>=1.34.0; extra == "all"
Requires-Dist: large-image-source-multi[all]>=1.34.0; extra == "all"
Requires-Dist: tol-colors>=2.0.0; extra == "all"
Requires-Dist: large-image-source-mapnik>=1.34.0; extra == "all"
Requires-Dist: large-image-source-gdal>=1.34.0; extra == "all"
Requires-Dist: large-image-source-dummy>=1.34.0; extra == "all"
Requires-Dist: large-image-source-tifffile>=1.34.0; extra == "all"
Requires-Dist: large-image-source-tiff>=1.34.0; extra == "all"
Requires-Dist: large-image-source-deepzoom>=1.34.0; extra == "all"
Requires-Dist: large-image-source-ometiff>=1.34.0; extra == "all"
Requires-Dist: large-image-converter>=1.34.0; extra == "all"
Provides-Extra: common
Requires-Dist: large-image-source-rasterio[all]>=1.34.0; extra == "common"
Requires-Dist: large-image-source-nd2>=1.34.0; extra == "common"
Requires-Dist: large-image-source-dicom>=1.34.0; extra == "common"
Requires-Dist: matplotlib; extra == "common"
Requires-Dist: large-image-source-openslide>=1.34.0; extra == "common"
Requires-Dist: large-image-source-zarr>=1.34.0; extra == "common"
Requires-Dist: tol-colors>=2.0.0; extra == "common"
Requires-Dist: large-image-source-test>=1.34.0; extra == "common"
Requires-Dist: large-image-source-tifffile>=1.34.0; extra == "common"
Requires-Dist: large-image-source-multi>=1.34.0; extra == "common"
Requires-Dist: psutil>=4.2.0; extra == "common"
Requires-Dist: large-image-source-pil[common]>=1.34.0; extra == "common"
Requires-Dist: simplejpeg; extra == "common"
Requires-Dist: large-image-source-deepzoom>=1.34.0; extra == "common"
Dynamic: author
Dynamic: author-email
Dynamic: classifier
Dynamic: description
Dynamic: description-content-type
Dynamic: home-page
Dynamic: keywords
Dynamic: license
Dynamic: license-file
Dynamic: provides-extra
Dynamic: requires-dist
Dynamic: requires-python
Dynamic: summary
